{"legislature":"42nd","session":"3rd","volume":"58b","type":"house","link":"vol_58b/h58b.html","key":"42nd3rd58b","date":"2021-04-29T05:00:00.000Z","committee":"LEGISLATIVE\nASSEMBLY OF MANITOBA","speakers":["Doyle Piwniuk","Adrien Sala","Nahanni Fontaine","Kelvin Goertzen","Uzoma Asagwara","Jon Gerrard","Audrey Gordon","Bernadette Smith","Cindy Lamoureux","Ron Schuler","Amanda Lathlin","Andrew Smith","Mintu Sandhu","Dougald Lamont","Wab Kinew","Brian Pallister","Nello Altomare","Cliff Cullen","Tom Lindsey","Scott Fielding","Mark Wasyliw","Len Isleifson","Cameron Friesen","Ian Bushie","Jim Maloway","Jamie Moses","Malaya Marcelino","Dennis Smook","Matt Wiebe"]}